plasmidhub/__init__.py
plasmidhub/abricate.py
plasmidhub/ani.py
plasmidhub/cluster_color.py
plasmidhub/clustering.py
plasmidhub/filtering.py
plasmidhub/main.py
plasmidhub/network_builder.py
plasmidhub/node_stats.py
plasmidhub/plot.py
plasmidhub/plot_only.py
plasmidhub/preprocessing.py
plasmidhub-1.0.1.dist-info/LICENSE
plasmidhub-1.0.1.dist-info/METADATA
plasmidhub-1.0.1.dist-info/WHEEL
plasmidhub-1.0.1.dist-info/entry_points.txt
plasmidhub-1.0.1.dist-info/top_level.txt
plasmidhub-1.0.1.dist-info/RECORD
