Metadata-Version: 2.1
Name: plasmidhub
Version: 1.0.1
Summary: A command-line tool for plasmid clustering, analysis, and visualization.
Author-email: "Dr. Balint Timmer" <timmer.balint@med.unideb.hu>
License: GNU GENERAL PUBLIC LICENSE
Keywords: plasmid,bioinformatics,network,clustering,AMR,virulence,plasmid network
Classifier: Programming Language :: Python :: 3
Classifier: License :: OSI Approved :: GNU General Public License v3 (GPLv3)
Classifier: Operating System :: OS Independent
Classifier: Intended Audience :: Science/Research
Classifier: Topic :: Scientific/Engineering :: Bio-Informatics
Requires-Python: >=3.8
License-File: LICENSE
Requires-Dist: biopython>=1.83
Requires-Dist: pandas>=2.0
Requires-Dist: networkx>=3.1
Requires-Dist: matplotlib>=3.7
Requires-Dist: python-louvain>=0.16
Requires-Dist: numpy>=1.24
Requires-Dist: scipy>=1.8
Provides-Extra: dev
Requires-Dist: pytest; extra == "dev"
